keyword_extractor/__init__.py
keyword_extractor/keyword_extractor.py
bn_keyword_extractor-1.0.2.dist-info/METADATA
bn_keyword_extractor-1.0.2.dist-info/WHEEL
bn_keyword_extractor-1.0.2.dist-info/top_level.txt
bn_keyword_extractor-1.0.2.dist-info/RECORD
